amundsenatlastypes/__init__.py
amundsenatlastypes/client.py
amundsenatlastypes/sample_data.py
amundsenatlastypes/types_def.py
amundsenatlastypes/schema/01_1_reader.json
amundsenatlastypes/schema/01_2_table_schema.json
amundsenatlastypes/schema/01_3_bookmark.json
amundsenatlastypes/schema/01_4_report.json
amundsenatlastypes/schema/01_column_schema.json
amundsenatlastypes/schema/02_user.json
amundsenatlastypes/schema/04_reader_referenceable_relation.json
amundsenatlastypes/schema/04_user_reader_relation.json
amundsenatlastypes/schema/05_1_hive_table_partition.json
amundsenatlastypes/schema/05_table_partition_schema.json
amundsenatlastypes/schema/06_user_table_owner_relation.json
amundsenatlastypes/schema/__init__.py
amundsenatlastypes/schema/test.py
amundsenatlastypes/schema/dashboard/01_group.json
amundsenatlastypes/schema/dashboard/02_dashboard.json
amundsenatlastypes/schema/dashboard/03_query.json
amundsenatlastypes/schema/dashboard/04_chart.json
amundsenatlastypes/schema/dashboard/05_execution.json
amundsenatlastypes/schema/dashboard/__init__.py
amundsenatlastypes/schema/dashboard/sample_data.py
amundsenatlastypes/schema/table/__init__.py
amundsenatlastypes/schema/table/sample_data.py
amundsenatlastypes-1.2.2.dist-info/LICENSE
amundsenatlastypes-1.2.2.dist-info/METADATA
amundsenatlastypes-1.2.2.dist-info/WHEEL
amundsenatlastypes-1.2.2.dist-info/top_level.txt
amundsenatlastypes-1.2.2.dist-info/RECORD
