Metadata-Version: 2.1
Name: amundsenatlastypes
Version: 1.2.2
Summary: Custom Amundsen Atlas data types definition
Home-page: https://github.com/dwarszawski/amundsen-atlas-types
Author: Damian Warszawski
Maintainer: Mariusz Górski
Maintainer-email: gorskimariusz13@gmail.com
License: Apache Software License 2.0
Keywords: apache atlas,atlas types,amundsen,amundsen atlas
Platform: UNKNOWN
Classifier: Development Status :: 5 - Production/Stable
Classifier: Intended Audience :: Developers
Classifier: License :: OSI Approved :: Apache Software License
Classifier: Natural Language :: English
Classifier: Programming Language :: Python :: 2
Classifier: Programming Language :: Python :: 2.7
Classifier: Programming Language :: Python :: 3
Classifier: Programming Language :: Python :: 3.5
Classifier: Programming Language :: Python :: 3.6
Requires-Dist: pyatlasclient
Provides-Extra: dev
Requires-Dist: mypy ; extra == 'dev'
Requires-Dist: flake8 ; extra == 'dev'
Provides-Extra: samples
Requires-Dist: faker ; extra == 'samples'
